dvol/__init__.py
dvol/__main__.py
dvol/cli.py
dvol/commands/__init__.py
dvol/commands/add.py
dvol/commands/config.py
dvol/commands/disable.py
dvol/commands/enable.py
dvol/commands/get.py
dvol/commands/main.py
dvol/commands/remove.py
dvol/dvol_helpers/__init__.py
dvol/dvol_helpers/common.py
dvol/dvol_helpers/compose_tools.py
dvol/dvol_helpers/config.py
dvol/dvol_helpers/docker_tools.py
dvol/dvol_helpers/dvol_add.py
dvol/dvol_helpers/dvol_print.py
dvol/dvol_helpers/dvol_remove.py
dvol-0.1.0.dist-info/LICENSE
dvol-0.1.0.dist-info/METADATA
dvol-0.1.0.dist-info/WHEEL
dvol-0.1.0.dist-info/entry_points.txt
dvol-0.1.0.dist-info/top_level.txt
dvol-0.1.0.dist-info/RECORD
